{
  "page": {
    "id": "r3y8hrtg97vy",
    "name": "Network & Infrastructure",
    "url": "https://network.status-ovhcloud.com",
    "time_zone": "Etc/UTC",
    "updated_at": "2022-06-16T07:00:38.686Z"
  },
  "components": [
    {
      "id": "66ctp89pwlcd",
      "name": "GRA1",
      "status": "operational",
      "created_at": "2021-11-10T14:20:37.816Z",
      "updated_at": "2022-06-16T02:03:40.679Z",
      "position": 1,
      "description": null,
      "showcase": false,
      "start_date": "2021-11-10",
      "group_id": "cxhdwyc4lvgf",
      "page_id": "r3y8hrtg97vy",
      "group": false,
      "only_show_if_degraded": false
    },
    {
      "id": "s6fd9v65w7c3",
      "name": "SYD1",
      "status": "operational",
      "created_at": "2021-11-10T14:20:08.513Z",
      "updated_at": "2022-05-16T23:44:57.782Z",
      "position": 1,
      "description": null,
      "showcase": false,
      "start_date": "2021-11-10",
      "group_id": "b2zrcdtcfxpw",
      "page_id": "r3y8hrtg97vy",
      "group": false,
      "only_show_if_degraded": false
    },
    {
      "id": "l38v4l1b1vt8",
      "name": "ERI1",
      "status": "operational",
      "created_at": "2021-11-10T14:20:45.650Z",
      "updated_at": "2022-06-15T18:57:20.299Z",
      "position": 1,
      "description": null,
      "showcase": false,
      "start_date": "2021-11-10",
      "group_id": "sdpm85zsx4w3",
      "page_id": "r3y8hrtg97vy",
      "group": false,
      "only_show_if_degraded": false
    },
    {
      "id": "xxvy97qsff1g",
      "name": "Infrastructure || Backbone",
      "status": "under_maintenance",
      "created_at": "2022-05-20T08:38:13.277Z",
      "updated_at": "2022-06-16T07:00:38.596Z",
      "position": 1,
      "description": null,
      "showcase": false,
      "start_date": "2022-05-20",
      "group_id": null,
      "page_id": "r3y8hrtg97vy",
      "group": false,
      "only_show_if_degraded": false
    },
    {
      "id": "yn247hwpljdf",
      "name": "BHS1",
      "status": "operational",
      "created_at": "2021-11-10T14:20:26.643Z",
      "updated_at": "2022-06-08T03:00:31.952Z",
      "position": 1,
      "description": null,
      "showcase": false,
      "start_date": "2021-11-10",
      "group_id": "p5hsr9gwdmns",
      "page_id": "r3y8hrtg97vy",
      "group": false,
      "only_show_if_degraded": false
    },
    {
      "id": "f4dnnwz43vr4",
      "name": "RBX1",
      "status": "operational",
      "created_at": "2021-11-10T14:20:15.203Z",
      "updated_at": "2022-06-14T12:39:25.778Z",
      "position": 1,
      "description": null,
      "showcase": false,
      "start_date": "2021-11-10",
      "group_id": "zllgrccdn4nk",
      "page_id": "r3y8hrtg97vy",
      "group": false,
      "only_show_if_degraded": false
    },
    {
      "id": "22t7pf7c6ky1",
      "name": "LIM1",
      "status": "operational",
      "created_at": "2021-11-10T14:19:53.034Z",
      "updated_at": "2022-06-10T01:50:36.080Z",
      "position": 1,
      "description": null,
      "showcase": false,
      "start_date": "2021-11-10",
      "group_id": "vmrgldv3x56g",
      "page_id": "r3y8hrtg97vy",
      "group": false,
      "only_show_if_degraded": false
    },
    {
      "id": "2k7jxkf0w8f4",
      "name": "SBG1",
      "status": "under_maintenance",
      "created_at": "2021-11-10T14:20:00.223Z",
      "updated_at": "2022-06-16T06:01:33.973Z",
      "position": 1,
      "description": null,
      "showcase": false,
      "start_date": "2021-11-10",
      "group_id": "vhfy3slw3nj2",
      "page_id": "r3y8hrtg97vy",
      "group": false,
      "only_show_if_degraded": false
    },
    {
      "id": "p5jg5r8hjzk6",
      "name": "RBX2",
      "status": "operational",
      "created_at": "2021-11-10T14:20:15.916Z",
      "updated_at": "2022-06-08T14:34:04.257Z",
      "position": 2,
      "description": null,
      "showcase": false,
      "start_date": "2021-11-10",
      "group_id": "zllgrccdn4nk",
      "page_id": "r3y8hrtg97vy",
      "group": false,
      "only_show_if_degraded": false
    },
    {
      "id": "n3pn0f28b99n",
      "name": "SBG3",
      "status": "under_maintenance",
      "created_at": "2021-11-10T14:20:01.143Z",
      "updated_at": "2022-06-16T06:01:34.027Z",
      "position": 2,
      "description": null,
      "showcase": false,
      "start_date": "2021-11-10",
      "group_id": "vhfy3slw3nj2",
      "page_id": "r3y8hrtg97vy",
      "group": false,
      "only_show_if_degraded": false
    },
    {
      "id": "f4vdn73g6790",
      "name": "GRA2",
      "status": "under_maintenance",
      "created_at": "2021-11-10T14:20:38.598Z",
      "updated_at": "2022-06-15T14:34:47.424Z",
      "position": 2,
      "description": null,
      "showcase": false,
      "start_date": "2021-11-10",
      "group_id": "cxhdwyc4lvgf",
      "page_id": "r3y8hrtg97vy",
      "group": false,
      "only_show_if_degraded": false
    },
    {
      "id": "zlmhfg14mvn6",
      "name": "SYD2",
      "status": "operational",
      "created_at": "2021-11-10T14:20:09.250Z",
      "updated_at": "2022-05-12T17:01:18.509Z",
      "position": 2,
      "description": null,
      "showcase": false,
      "start_date": "2021-11-10",
      "group_id": "b2zrcdtcfxpw",
      "page_id": "r3y8hrtg97vy",
      "group": false,
      "only_show_if_degraded": false
    },
    {
      "id": "5xq7xnb7ytpx",
      "name": "LIM2",
      "status": "operational",
      "created_at": "2021-11-10T14:19:53.837Z",
      "updated_at": "2022-05-13T20:41:04.265Z",
      "position": 2,
      "description": null,
      "showcase": false,
      "start_date": "2021-11-10",
      "group_id": "vmrgldv3x56g",
      "page_id": "r3y8hrtg97vy",
      "group": false,
      "only_show_if_degraded": false
    },
    {
      "id": "p5hsr9gwdmns",
      "name": "Infrastructure || BHS",
      "status": "operational",
      "created_at": "2021-11-10T14:20:32.796Z",
      "updated_at": "2022-05-20T08:40:07.510Z",
      "position": 2,
      "description": null,
      "showcase": false,
      "start_date": null,
      "group_id": null,
      "page_id": "r3y8hrtg97vy",
      "group": true,
      "only_show_if_degraded": false,
      "components": [
        "yn247hwpljdf",
        "snrc66fccrvf",
        "rx2j2wt4xylz",
        "wjpq5n3hnjhx",
        "c8f6gqd9ns9h",
        "33xy09j449pk",
        "v0kyk7zsjqvd",
        "m4pzrlrxvvgt"
      ]
    },
    {
      "id": "snrc66fccrvf",
      "name": "BHS2",
      "status": "operational",
      "created_at": "2021-11-10T14:20:27.348Z",
      "updated_at": "2022-06-09T02:50:16.213Z",
      "position": 2,
      "description": null,
      "showcase": false,
      "start_date": "2021-11-10",
      "group_id": "p5hsr9gwdmns",
      "page_id": "r3y8hrtg97vy",
      "group": false,
      "only_show_if_degraded": false
    },
    {
      "id": "sdpm85zsx4w3",
      "name": "Infrastructure || ERI",
      "status": "operational",
      "created_at": "2021-11-10T14:20:46.526Z",
      "updated_at": "2022-05-20T08:40:39.771Z",
      "position": 3,
      "description": null,
      "showcase": false,
      "start_date": null,
      "group_id": null,
      "page_id": "r3y8hrtg97vy",
      "group": true,
      "only_show_if_degraded": false,
      "components": [
        "l38v4l1b1vt8"
      ]
    },
    {
      "id": "n39cfc7qz4vh",
      "name": "SBG4",
      "status": "under_maintenance",
      "created_at": "2021-11-10T14:20:01.976Z",
      "updated_at": "2022-06-16T06:01:34.060Z",
      "position": 3,
      "description": null,
      "showcase": false,
      "start_date": "2021-11-10",
      "group_id": "vhfy3slw3nj2",
      "page_id": "r3y8hrtg97vy",
      "group": false,
      "only_show_if_degraded": false
    },
    {
      "id": "mlw1x23q8nrt",
      "name": "GRA3",
      "status": "operational",
      "created_at": "2021-11-10T14:20:39.377Z",
      "updated_at": "2022-06-08T07:24:19.811Z",
      "position": 3,
      "description": null,
      "showcase": false,
      "start_date": "2021-11-10",
      "group_id": "cxhdwyc4lvgf",
      "page_id": "r3y8hrtg97vy",
      "group": false,
      "only_show_if_degraded": false
    },
    {
      "id": "gmpjyy3kgdlv",
      "name": "RBX3",
      "status": "operational",
      "created_at": "2021-11-10T14:20:17.105Z",
      "updated_at": "2022-06-07T05:48:20.123Z",
      "position": 3,
      "description": null,
      "showcase": false,
      "start_date": "2021-11-10",
      "group_id": "zllgrccdn4nk",
      "page_id": "r3y8hrtg97vy",
      "group": false,
      "only_show_if_degraded": false
    },
    {
      "id": "krxvw2yfrj4f",
      "name": "LIM3",
      "status": "operational",
      "created_at": "2021-11-10T14:19:54.583Z",
      "updated_at": "2022-05-16T23:16:44.885Z",
      "position": 3,
      "description": null,
      "showcase": false,
      "start_date": "2021-11-10",
      "group_id": "vmrgldv3x56g",
      "page_id": "r3y8hrtg97vy",
      "group": false,
      "only_show_if_degraded": false
    },
    {
      "id": "rx2j2wt4xylz",
      "name": "BHS3",
      "status": "operational",
      "created_at": "2021-11-10T14:20:28.104Z",
      "updated_at": "2022-05-16T09:01:16.456Z",
      "position": 3,
      "description": null,
      "showcase": false,
      "start_date": "2021-11-10",
      "group_id": "p5hsr9gwdmns",
      "page_id": "r3y8hrtg97vy",
      "group": false,
      "only_show_if_degraded": false
    },
    {
      "id": "ztt6jttbfmcr",
      "name": "RBX4",
      "status": "operational",
      "created_at": "2021-11-10T14:20:17.852Z",
      "updated_at": "2022-06-14T12:34:20.711Z",
      "position": 4,
      "description": null,
      "showcase": false,
      "start_date": "2021-11-10",
      "group_id": "zllgrccdn4nk",
      "page_id": "r3y8hrtg97vy",
      "group": false,
      "only_show_if_degraded": false
    },
    {
      "id": "cxhdwyc4lvgf",
      "name": "Infrastructure || GRA",
      "status": "under_maintenance",
      "created_at": "2021-11-10T14:20:40.180Z",
      "updated_at": "2022-05-20T08:40:50.176Z",
      "position": 4,
      "description": null,
      "showcase": false,
      "start_date": null,
      "group_id": null,
      "page_id": "r3y8hrtg97vy",
      "group": true,
      "only_show_if_degraded": false,
      "components": [
        "66ctp89pwlcd",
        "f4vdn73g6790",
        "mlw1x23q8nrt"
      ]
    },
    {
      "id": "wjpq5n3hnjhx",
      "name": "BHS4",
      "status": "operational",
      "created_at": "2021-11-10T14:20:28.786Z",
      "updated_at": "2022-06-09T19:16:07.915Z",
      "position": 4,
      "description": null,
      "showcase": false,
      "start_date": "2021-11-10",
      "group_id": "p5hsr9gwdmns",
      "page_id": "r3y8hrtg97vy",
      "group": false,
      "only_show_if_degraded": false
    },
    {
      "id": "vmrgldv3x56g",
      "name": "Infrastructure || LIM",
      "status": "operational",
      "created_at": "2021-11-10T14:19:55.284Z",
      "updated_at": "2022-05-20T08:41:00.406Z",
      "position": 5,
      "description": null,
      "showcase": false,
      "start_date": null,
      "group_id": null,
      "page_id": "r3y8hrtg97vy",
      "group": true,
      "only_show_if_degraded": false,
      "components": [
        "22t7pf7c6ky1",
        "5xq7xnb7ytpx",
        "krxvw2yfrj4f"
      ]
    },
    {
      "id": "n3bn7csv5k3k",
      "name": "RBX5",
      "status": "operational",
      "created_at": "2021-11-10T14:20:18.529Z",
      "updated_at": "2022-06-07T05:48:20.147Z",
      "position": 5,
      "description": null,
      "showcase": false,
      "start_date": "2021-11-10",
      "group_id": "zllgrccdn4nk",
      "page_id": "r3y8hrtg97vy",
      "group": false,
      "only_show_if_degraded": false
    },
    {
      "id": "c8f6gqd9ns9h",
      "name": "BHS5",
      "status": "operational",
      "created_at": "2021-11-10T14:20:29.578Z",
      "updated_at": "2022-05-26T02:12:29.115Z",
      "position": 5,
      "description": null,
      "showcase": false,
      "start_date": "2021-11-10",
      "group_id": "p5hsr9gwdmns",
      "page_id": "r3y8hrtg97vy",
      "group": false,
      "only_show_if_degraded": false
    },
    {
      "id": "5rlwxw2f24qh",
      "name": "RBX6",
      "status": "operational",
      "created_at": "2021-11-10T14:20:19.265Z",
      "updated_at": "2022-06-14T03:01:13.430Z",
      "position": 6,
      "description": null,
      "showcase": false,
      "start_date": "2021-11-10",
      "group_id": "zllgrccdn4nk",
      "page_id": "r3y8hrtg97vy",
      "group": false,
      "only_show_if_degraded": false
    },
    {
      "id": "33xy09j449pk",
      "name": "BHS6",
      "status": "operational",
      "created_at": "2021-11-10T14:20:30.507Z",
      "updated_at": "2022-06-14T12:43:16.969Z",
      "position": 6,
      "description": null,
      "showcase": false,
      "start_date": "2021-11-10",
      "group_id": "p5hsr9gwdmns",
      "page_id": "r3y8hrtg97vy",
      "group": false,
      "only_show_if_degraded": false
    },
    {
      "id": "l6lvwt05kh0j",
      "name": "Infrastructure || P19",
      "status": "operational",
      "created_at": "2021-11-10T14:20:53.084Z",
      "updated_at": "2022-05-20T08:41:11.227Z",
      "position": 6,
      "description": null,
      "showcase": false,
      "start_date": "2021-11-10",
      "group_id": null,
      "page_id": "r3y8hrtg97vy",
      "group": false,
      "only_show_if_degraded": false
    },
    {
      "id": "02w2qqv00ll9",
      "name": "RBX7",
      "status": "under_maintenance",
      "created_at": "2021-11-10T14:20:20.034Z",
      "updated_at": "2022-06-14T12:44:12.111Z",
      "position": 7,
      "description": null,
      "showcase": false,
      "start_date": "2021-11-10",
      "group_id": "zllgrccdn4nk",
      "page_id": "r3y8hrtg97vy",
      "group": false,
      "only_show_if_degraded": false
    },
    {
      "id": "zllgrccdn4nk",
      "name": "Infrastructure || RBX",
      "status": "under_maintenance",
      "created_at": "2021-11-10T14:20:21.603Z",
      "updated_at": "2022-05-20T08:41:22.303Z",
      "position": 7,
      "description": null,
      "showcase": false,
      "start_date": null,
      "group_id": null,
      "page_id": "r3y8hrtg97vy",
      "group": true,
      "only_show_if_degraded": false,
      "components": [
        "f4dnnwz43vr4",
        "p5jg5r8hjzk6",
        "gmpjyy3kgdlv",
        "ztt6jttbfmcr",
        "n3bn7csv5k3k",
        "5rlwxw2f24qh",
        "02w2qqv00ll9",
        "lpwtkmwp5rr2"
      ]
    },
    {
      "id": "v0kyk7zsjqvd",
      "name": "BHS7",
      "status": "operational",
      "created_at": "2021-11-10T14:20:31.279Z",
      "updated_at": "2022-06-08T23:29:44.157Z",
      "position": 7,
      "description": null,
      "showcase": false,
      "start_date": "2021-11-10",
      "group_id": "p5hsr9gwdmns",
      "page_id": "r3y8hrtg97vy",
      "group": false,
      "only_show_if_degraded": false
    },
    {
      "id": "lpwtkmwp5rr2",
      "name": "RBX8",
      "status": "operational",
      "created_at": "2021-11-10T14:20:20.804Z",
      "updated_at": "2022-06-14T16:50:27.219Z",
      "position": 8,
      "description": null,
      "showcase": false,
      "start_date": "2021-11-10",
      "group_id": "zllgrccdn4nk",
      "page_id": "r3y8hrtg97vy",
      "group": false,
      "only_show_if_degraded": false
    },
    {
      "id": "m4pzrlrxvvgt",
      "name": "BHS8",
      "status": "operational",
      "created_at": "2021-11-10T14:20:32.046Z",
      "updated_at": "2022-06-15T03:07:26.468Z",
      "position": 8,
      "description": null,
      "showcase": false,
      "start_date": "2021-11-10",
      "group_id": "p5hsr9gwdmns",
      "page_id": "r3y8hrtg97vy",
      "group": false,
      "only_show_if_degraded": false
    },
    {
      "id": "vhfy3slw3nj2",
      "name": "Infrastructure || SBG",
      "status": "under_maintenance",
      "created_at": "2021-11-10T14:20:03.647Z",
      "updated_at": "2022-05-20T08:41:34.781Z",
      "position": 8,
      "description": null,
      "showcase": false,
      "start_date": null,
      "group_id": null,
      "page_id": "r3y8hrtg97vy",
      "group": true,
      "only_show_if_degraded": false,
      "components": [
        "2k7jxkf0w8f4",
        "n3pn0f28b99n",
        "n39cfc7qz4vh"
      ]
    },
    {
      "id": "bs5xcsc4m9vm",
      "name": "Infrastructure || SGP1",
      "status": "operational",
      "created_at": "2021-11-10T14:20:53.904Z",
      "updated_at": "2022-06-15T02:11:12.771Z",
      "position": 9,
      "description": null,
      "showcase": false,
      "start_date": "2021-11-10",
      "group_id": null,
      "page_id": "r3y8hrtg97vy",
      "group": false,
      "only_show_if_degraded": false
    },
    {
      "id": "b2zrcdtcfxpw",
      "name": "Infrastructure || SYD",
      "status": "operational",
      "created_at": "2021-11-10T14:20:09.976Z",
      "updated_at": "2022-05-20T08:42:13.379Z",
      "position": 10,
      "description": null,
      "showcase": false,
      "start_date": null,
      "group_id": null,
      "page_id": "r3y8hrtg97vy",
      "group": true,
      "only_show_if_degraded": false,
      "components": [
        "s6fd9v65w7c3",
        "zlmhfg14mvn6"
      ]
    },
    {
      "id": "84zk3wk4nv6k",
      "name": "Infrastructure || WAW1",
      "status": "operational",
      "created_at": "2021-11-10T14:20:54.627Z",
      "updated_at": "2022-06-15T02:11:12.783Z",
      "position": 11,
      "description": null,
      "showcase": false,
      "start_date": "2021-11-10",
      "group_id": null,
      "page_id": "r3y8hrtg97vy",
      "group": false,
      "only_show_if_degraded": false
    },
    {
      "id": "09f41qrzqycc",
      "name": "Network Services || OVHcloud Load Balancer",
      "status": "operational",
      "created_at": "2021-11-10T14:20:50.064Z",
      "updated_at": "2022-05-20T08:38:57.802Z",
      "position": 12,
      "description": null,
      "showcase": false,
      "start_date": "2021-11-10",
      "group_id": null,
      "page_id": "r3y8hrtg97vy",
      "group": false,
      "only_show_if_degraded": false
    },
    {
      "id": "pgf35fxt4ywk",
      "name": "Network Services || vRack Private Network",
      "status": "operational",
      "created_at": "2022-05-20T08:36:07.479Z",
      "updated_at": "2022-05-20T08:38:57.869Z",
      "position": 25,
      "description": null,
      "showcase": false,
      "start_date": "2022-05-20",
      "group_id": null,
      "page_id": "r3y8hrtg97vy",
      "group": false,
      "only_show_if_degraded": false
    },
    {
      "id": "7dqfjv25ylgc",
      "name": "Network Services || OVHcloud Connect",
      "status": "operational",
      "created_at": "2022-05-20T08:36:35.578Z",
      "updated_at": "2022-05-20T08:38:57.874Z",
      "position": 26,
      "description": null,
      "showcase": false,
      "start_date": "2022-05-20",
      "group_id": null,
      "page_id": "r3y8hrtg97vy",
      "group": false,
      "only_show_if_degraded": false
    },
    {
      "id": "ng50wn5dw8g6",
      "name": "Network Services || Failover IP (Public IP)",
      "status": "operational",
      "created_at": "2022-05-20T08:37:15.827Z",
      "updated_at": "2022-05-20T08:38:57.879Z",
      "position": 27,
      "description": null,
      "showcase": false,
      "start_date": "2022-05-20",
      "group_id": null,
      "page_id": "r3y8hrtg97vy",
      "group": false,
      "only_show_if_degraded": false
    }
  ],
  "incidents": [],
  "scheduled_maintenances": [
    {
      "id": "xhyn0j0k0xrf",
      "name": "[GRA2][Cooling System] - G243B09",
      "status": "scheduled",
      "created_at": "2022-04-26T07:00:56.074Z",
      "updated_at": "2022-04-26T08:00:24.191Z",
      "monitoring_at": null,
      "resolved_at": null,
      "impact": "maintenance",
      "shortlink": "https://stspg.io/j7837xsk7tsx",
      "started_at": "2022-04-26T07:00:56.067Z",
      "page_id": "r3y8hrtg97vy",
      "incident_updates": [
        {
          "id": "ktz59mvqdhbq",
          "status": "scheduled",
          "body": "Maintenance will begin as scheduled in 60 minutes.",
          "incident_id": "xhyn0j0k0xrf",
          "created_at": "2022-04-26T08:00:23.947Z",
          "updated_at": "2022-04-26T08:00:23.947Z",
          "display_at": "2022-04-26T08:00:23.947Z",
          "affected_components": null,
          "deliver_notifications": true,
          "custom_tweet": null,
          "tweet_id": null
        },
        {
          "id": "y87g6cc9vfvw",
          "status": "scheduled",
          "body": "<b>Start time :</b> 26/04/2022 06:00 UTC\n<b>End time :</b> 27/04/2022 14:00 UTC\n<b>Service impact :</b> None\n<b>Service improvement :</b> Water manifold replacement",
          "incident_id": "xhyn0j0k0xrf",
          "created_at": "2022-04-26T07:00:56.124Z",
          "updated_at": "2022-04-26T07:00:56.124Z",
          "display_at": "2022-04-26T07:00:56.124Z",
          "affected_components": [
            {
              "code": "66ctp89pwlcd",
              "name": "Datacenters || GRA - GRA1",
              "old_status": "under_maintenance",
              "new_status": "under_maintenance"
            }
          ],
          "deliver_notifications": true,
          "custom_tweet": null,
          "tweet_id": null
        }
      ],
      "components": [
        {
          "id": "66ctp89pwlcd",
          "name": "GRA1",
          "status": "operational",
          "created_at": "2021-11-10T14:20:37.816Z",
          "updated_at": "2022-06-16T02:03:40.679Z",
          "position": 1,
          "description": null,
          "showcase": false,
          "start_date": "2021-11-10",
          "group_id": "cxhdwyc4lvgf",
          "page_id": "r3y8hrtg97vy",
          "group": false,
          "only_show_if_degraded": false
        }
      ],
      "scheduled_for": "2022-04-26T09:00:00.000Z",
      "scheduled_until": "2022-04-27T02:00:00.000Z"
    },
    {
      "id": "0xll61mm8ky9",
      "name": "[BHS4][Cooling System] - T04E06",
      "status": "scheduled",
      "created_at": "2022-06-14T10:11:54.761Z",
      "updated_at": "2022-06-14T10:20:17.339Z",
      "monitoring_at": null,
      "resolved_at": null,
      "impact": "maintenance",
      "shortlink": "https://stspg.io/3jd2g7gk1985",
      "started_at": "2022-06-14T10:11:54.754Z",
      "page_id": "r3y8hrtg97vy",
      "incident_updates": [
        {
          "id": "06zzxxycb8q3",
          "status": "scheduled",
          "body": "<b>Start time :</b> 16/06/2022 11:00 UTC\n<b>End time :</b> 17/06/2022 03:00 UTC\n<b>Service impact :</b> None\n<b>Service improvement :</b> Water manifold replacement",
          "incident_id": "0xll61mm8ky9",
          "created_at": "2022-06-14T10:11:54.809Z",
          "updated_at": "2022-06-14T10:11:54.809Z",
          "display_at": "2022-06-14T10:11:54.809Z",
          "affected_components": [
            {
              "code": "wjpq5n3hnjhx",
              "name": "Infrastructure || BHS - BHS4",
              "old_status": "operational",
              "new_status": "operational"
            }
          ],
          "deliver_notifications": true,
          "custom_tweet": null,
          "tweet_id": null
        }
      ],
      "components": [
        {
          "id": "wjpq5n3hnjhx",
          "name": "BHS4",
          "status": "operational",
          "created_at": "2021-11-10T14:20:28.786Z",
          "updated_at": "2022-06-09T19:16:07.915Z",
          "position": 4,
          "description": null,
          "showcase": false,
          "start_date": "2021-11-10",
          "group_id": "p5hsr9gwdmns",
          "page_id": "r3y8hrtg97vy",
          "group": false,
          "only_show_if_degraded": false
        }
      ],
      "scheduled_for": "2022-06-16T11:00:00.000Z",
      "scheduled_until": "2022-06-17T01:40:00.000Z"
    },
    {
      "id": "0k3k36vlr9vw",
      "name": "[GRA1][vRack] - Network Maintenance Notification",
      "status": "scheduled",
      "created_at": "2022-06-08T08:51:18.584Z",
      "updated_at": "2022-06-13T08:11:53.108Z",
      "monitoring_at": null,
      "resolved_at": null,
      "impact": "maintenance",
      "shortlink": "https://stspg.io/rrknlhn85vmd",
      "started_at": "2022-06-08T08:51:18.578Z",
      "page_id": "r3y8hrtg97vy",
      "incident_updates": [
        {
          "id": "3p8d3lk4nhpx",
          "status": "scheduled",
          "body": "Maintenance is postponed to the following date and time:\n<b>Start time :</b> 16/06/2022 20:00 UTC\n<b>End time :</b> 16/06/2022 21:30 UTC",
          "incident_id": "0k3k36vlr9vw",
          "created_at": "2022-06-13T08:11:53.106Z",
          "updated_at": "2022-06-13T08:11:53.106Z",
          "display_at": "2022-06-13T08:11:53.106Z",
          "affected_components": [
            {
              "code": "pgf35fxt4ywk",
              "name": "Network Services || vRack Private Network",
              "old_status": "operational",
              "new_status": "operational"
            }
          ],
          "deliver_notifications": true,
          "custom_tweet": null,
          "tweet_id": null
        },
        {
          "id": "myb9y7w12pdw",
          "status": "scheduled",
          "body": "<b>Start time :</b> 16/06/2022 18:00 UTC\n<b>End time :</b> 16/06/2022 19:30 UTC\n<b>Service impact :</b> 15min loss of connectivity during reloading of network equipment.\n<b>Service improvement :</b> Due to faulty ports and bugs, we have to reload a network device to solve the problems.",
          "incident_id": "0k3k36vlr9vw",
          "created_at": "2022-06-08T08:51:18.643Z",
          "updated_at": "2022-06-08T09:25:17.435Z",
          "display_at": "2022-06-08T08:51:18.643Z",
          "affected_components": [
            {
              "code": "pgf35fxt4ywk",
              "name": "Network Services || vRack Private Network",
              "old_status": "operational",
              "new_status": "operational"
            }
          ],
          "deliver_notifications": true,
          "custom_tweet": null,
          "tweet_id": null
        }
      ],
      "components": [
        {
          "id": "pgf35fxt4ywk",
          "name": "Network Services || vRack Private Network",
          "status": "operational",
          "created_at": "2022-05-20T08:36:07.479Z",
          "updated_at": "2022-05-20T08:38:57.869Z",
          "position": 25,
          "description": null,
          "showcase": false,
          "start_date": "2022-05-20",
          "group_id": null,
          "page_id": "r3y8hrtg97vy",
          "group": false,
          "only_show_if_degraded": false
        }
      ],
      "scheduled_for": "2022-06-16T20:00:00.000Z",
      "scheduled_until": "2022-06-16T21:30:00.000Z"
    },
    {
      "id": "9j0xlynhd19q",
      "name": "[GRA1][Network] - Network equipment version upgrade",
      "status": "scheduled",
      "created_at": "2022-06-13T15:33:39.210Z",
      "updated_at": "2022-06-13T15:33:39.263Z",
      "monitoring_at": null,
      "resolved_at": null,
      "impact": "maintenance",
      "shortlink": "https://stspg.io/575lmn57wn1n",
      "started_at": "2022-06-13T15:33:39.202Z",
      "page_id": "r3y8hrtg97vy",
      "incident_updates": [
        {
          "id": "hgvbd27krkc2",
          "status": "scheduled",
          "body": "<b>Start time :</b> 17/06/2022 00:00 UTC\n<b>End time :</b> 17/06/2022 03:00 UTC\n<b>Service impact :</b> None\n<b>Service improvement :</b> In order to maintain continuous improvement of our internal network infrastructure and to have a homogeneous park, we will upgrade the version of some network equipment.",
          "incident_id": "9j0xlynhd19q",
          "created_at": "2022-06-13T15:33:39.261Z",
          "updated_at": "2022-06-13T15:33:39.261Z",
          "display_at": "2022-06-13T15:33:39.261Z",
          "affected_components": [
            {
              "code": "66ctp89pwlcd",
              "name": "Infrastructure || GRA - GRA1",
              "old_status": "under_maintenance",
              "new_status": "under_maintenance"
            }
          ],
          "deliver_notifications": false,
          "custom_tweet": null,
          "tweet_id": null
        }
      ],
      "components": [
        {
          "id": "66ctp89pwlcd",
          "name": "GRA1",
          "status": "operational",
          "created_at": "2021-11-10T14:20:37.816Z",
          "updated_at": "2022-06-16T02:03:40.679Z",
          "position": 1,
          "description": null,
          "showcase": false,
          "start_date": "2021-11-10",
          "group_id": "cxhdwyc4lvgf",
          "page_id": "r3y8hrtg97vy",
          "group": false,
          "only_show_if_degraded": false
        }
      ],
      "scheduled_for": "2022-06-17T00:00:00.000Z",
      "scheduled_until": "2022-06-17T03:00:00.000Z"
    },
    {
      "id": "pbkrpm06vmlr",
      "name": "[LIM1][Infrastructure] - L111A19",
      "status": "scheduled",
      "created_at": "2022-06-08T20:09:23.986Z",
      "updated_at": "2022-06-14T14:31:11.095Z",
      "monitoring_at": null,
      "resolved_at": null,
      "impact": "maintenance",
      "shortlink": "https://stspg.io/156y5mvj6ll3",
      "started_at": "2022-06-08T20:09:23.977Z",
      "page_id": "r3y8hrtg97vy",
      "incident_updates": [
        {
          "id": "6jbryhsbt2yf",
          "status": "scheduled",
          "body": "Maintenance is postponed to the following date :\n<b>Start time :</b> 17/06/2022 08:30 UTC\n<b>End time :</b> 17/06/2022 18:00 UTC",
          "incident_id": "pbkrpm06vmlr",
          "created_at": "2022-06-14T14:31:11.090Z",
          "updated_at": "2022-06-14T14:31:11.090Z",
          "display_at": "2022-06-14T14:31:11.090Z",
          "affected_components": [
            {
              "code": "22t7pf7c6ky1",
              "name": "Infrastructure || LIM - LIM1",
              "old_status": "operational",
              "new_status": "operational"
            }
          ],
          "deliver_notifications": true,
          "custom_tweet": null,
          "tweet_id": null
        },
        {
          "id": "hx2k7pxv0kgc",
          "status": "scheduled",
          "body": "<b>Start time :</b> 15/06/2022 08:30 UTC\n<b>End time :</b> 15/06/2022 18:00 UTC\n<b>Service impact :</b> None\n<b>Service improvement :</b> As part of our continuous improvement of our infrastructure, we are doing an electrical maintenance on rack L111A19",
          "incident_id": "pbkrpm06vmlr",
          "created_at": "2022-06-08T20:09:24.039Z",
          "updated_at": "2022-06-08T20:09:24.039Z",
          "display_at": "2022-06-08T20:09:24.039Z",
          "affected_components": [
            {
              "code": "22t7pf7c6ky1",
              "name": "Infrastructure || LIM - LIM1",
              "old_status": "under_maintenance",
              "new_status": "under_maintenance"
            }
          ],
          "deliver_notifications": true,
          "custom_tweet": null,
          "tweet_id": null
        }
      ],
      "components": [
        {
          "id": "22t7pf7c6ky1",
          "name": "LIM1",
          "status": "operational",
          "created_at": "2021-11-10T14:19:53.034Z",
          "updated_at": "2022-06-10T01:50:36.080Z",
          "position": 1,
          "description": null,
          "showcase": false,
          "start_date": "2021-11-10",
          "group_id": "vmrgldv3x56g",
          "page_id": "r3y8hrtg97vy",
          "group": false,
          "only_show_if_degraded": false
        }
      ],
      "scheduled_for": "2022-06-17T08:30:00.000Z",
      "scheduled_until": "2022-06-17T18:00:00.000Z"
    },
    {
      "id": "1n3jkm2p2sfw",
      "name": "[RBX3][Infrastructure] - 41B04",
      "status": "scheduled",
      "created_at": "2022-06-14T18:44:46.872Z",
      "updated_at": "2022-06-14T18:44:46.930Z",
      "monitoring_at": null,
      "resolved_at": null,
      "impact": "maintenance",
      "shortlink": "https://stspg.io/8mm99r2776vn",
      "started_at": "2022-06-14T18:44:46.865Z",
      "page_id": "r3y8hrtg97vy",
      "incident_updates": [
        {
          "id": "vh5c04nmp31b",
          "status": "scheduled",
          "body": "<b>Start time :</b> 20/06/2022 04:00 UTC\n<b>End time :</b> 20/06/2022 05:00 UTC\n<b>Service impact :</b> The servers will be electrically cut off during maintenance.\n<b>Service improvement :</b> As part of our continuous improvement policy, we will be replacing a defective altigo.",
          "incident_id": "1n3jkm2p2sfw",
          "created_at": "2022-06-14T18:44:46.927Z",
          "updated_at": "2022-06-14T18:44:46.927Z",
          "display_at": "2022-06-14T18:44:46.927Z",
          "affected_components": [
            {
              "code": "gmpjyy3kgdlv",
              "name": "Infrastructure || RBX - RBX3",
              "old_status": "operational",
              "new_status": "operational"
            }
          ],
          "deliver_notifications": true,
          "custom_tweet": null,
          "tweet_id": null
        }
      ],
      "components": [
        {
          "id": "gmpjyy3kgdlv",
          "name": "RBX3",
          "status": "operational",
          "created_at": "2021-11-10T14:20:17.105Z",
          "updated_at": "2022-06-07T05:48:20.123Z",
          "position": 3,
          "description": null,
          "showcase": false,
          "start_date": "2021-11-10",
          "group_id": "zllgrccdn4nk",
          "page_id": "r3y8hrtg97vy",
          "group": false,
          "only_show_if_degraded": false
        }
      ],
      "scheduled_for": "2022-06-20T04:00:00.000Z",
      "scheduled_until": "2022-06-20T05:00:00.000Z"
    },
    {
      "id": "6x5nl93zqm4x",
      "name": "[SBG3][Cooling System] - Dry cooler MS6 maintenance",
      "status": "scheduled",
      "created_at": "2022-06-13T14:57:25.287Z",
      "updated_at": "2022-06-15T09:28:15.977Z",
      "monitoring_at": null,
      "resolved_at": null,
      "impact": "maintenance",
      "shortlink": "https://stspg.io/s3v4bb1xpvm4",
      "started_at": "2022-06-13T14:57:25.280Z",
      "page_id": "r3y8hrtg97vy",
      "incident_updates": [
        {
          "id": "v7gw9khc458y",
          "status": "scheduled",
          "body": "<b>Start time :</b> 16/06/2022 06:00 UTC\n<b>End time :</b> 16/06/2022 17:00 UTC\n<b>Service impact :</b> None\n<b>Service improvement :</b> As part of continuous improvement of our cooling infrastructure, we will be doing an internal maintenance on a dry cooler in SBG3.",
          "incident_id": "6x5nl93zqm4x",
          "created_at": "2022-06-13T14:57:25.334Z",
          "updated_at": "2022-06-15T09:28:15.972Z",
          "display_at": "2022-06-13T14:57:25.334Z",
          "affected_components": [
            {
              "code": "n3pn0f28b99n",
              "name": "Infrastructure || SBG - SBG3",
              "old_status": "operational",
              "new_status": "operational"
            }
          ],
          "deliver_notifications": false,
          "custom_tweet": null,
          "tweet_id": null
        }
      ],
      "components": [
        {
          "id": "n3pn0f28b99n",
          "name": "SBG3",
          "status": "under_maintenance",
          "created_at": "2021-11-10T14:20:01.143Z",
          "updated_at": "2022-06-16T06:01:34.027Z",
          "position": 2,
          "description": null,
          "showcase": false,
          "start_date": "2021-11-10",
          "group_id": "vhfy3slw3nj2",
          "page_id": "r3y8hrtg97vy",
          "group": false,
          "only_show_if_degraded": false
        }
      ],
      "scheduled_for": "2022-06-20T06:00:00.000Z",
      "scheduled_until": "2022-06-20T17:00:00.000Z"
    },
    {
      "id": "wbcqt0htzvcj",
      "name": "[SBG3][Cooling System] - Dry cooler MS7 maintenance",
      "status": "scheduled",
      "created_at": "2022-06-13T14:57:05.373Z",
      "updated_at": "2022-06-13T14:57:05.436Z",
      "monitoring_at": null,
      "resolved_at": null,
      "impact": "maintenance",
      "shortlink": "https://stspg.io/571jfklhhq39",
      "started_at": "2022-06-13T14:57:05.365Z",
      "page_id": "r3y8hrtg97vy",
      "incident_updates": [
        {
          "id": "4njg71n922nz",
          "status": "scheduled",
          "body": "<b>Start time :</b> 20/06/2022 06:00 UTC\n<b>End time :</b> 20/06/2022 17:00 UTC\n<b>Service impact :</b> None\n<b>Service improvement :</b> As part of continuous improvement of our cooling infrastructure, we will be doing an internal maintenance on a dry cooler in SBG3.",
          "incident_id": "wbcqt0htzvcj",
          "created_at": "2022-06-13T14:57:05.433Z",
          "updated_at": "2022-06-13T14:57:05.433Z",
          "display_at": "2022-06-13T14:57:05.433Z",
          "affected_components": [
            {
              "code": "n3pn0f28b99n",
              "name": "Infrastructure || SBG - SBG3",
              "old_status": "operational",
              "new_status": "operational"
            }
          ],
          "deliver_notifications": false,
          "custom_tweet": null,
          "tweet_id": null
        }
      ],
      "components": [
        {
          "id": "n3pn0f28b99n",
          "name": "SBG3",
          "status": "under_maintenance",
          "created_at": "2021-11-10T14:20:01.143Z",
          "updated_at": "2022-06-16T06:01:34.027Z",
          "position": 2,
          "description": null,
          "showcase": false,
          "start_date": "2021-11-10",
          "group_id": "vhfy3slw3nj2",
          "page_id": "r3y8hrtg97vy",
          "group": false,
          "only_show_if_degraded": false
        }
      ],
      "scheduled_for": "2022-06-20T06:00:00.000Z",
      "scheduled_until": "2022-06-20T17:00:00.000Z"
    },
    {
      "id": "c9pt4xxs15yv",
      "name": "[RBX2][Infrastructure] - Preventive maintenance for power delivery",
      "status": "scheduled",
      "created_at": "2022-04-25T12:37:05.258Z",
      "updated_at": "2022-04-25T12:37:05.313Z",
      "monitoring_at": null,
      "resolved_at": null,
      "impact": "maintenance",
      "shortlink": "https://stspg.io/c7x6bxdt1pq2",
      "started_at": "2022-04-25T12:37:05.250Z",
      "page_id": "r3y8hrtg97vy",
      "incident_updates": [
        {
          "id": "txs3hk73z6p4",
          "status": "scheduled",
          "body": "<b>Start time :</b> 20/06/2022 06:30 UTC\n<b>End time :</b> 20/06/2022 15:00 UTC\n<b>Service impact :</b> None\nFollowing a constructor's guideline, we're doing a maintenance on a power delivery component in redundancy.",
          "incident_id": "c9pt4xxs15yv",
          "created_at": "2022-04-25T12:37:05.311Z",
          "updated_at": "2022-04-25T12:37:05.311Z",
          "display_at": "2022-04-25T12:37:05.311Z",
          "affected_components": [
            {
              "code": "p5jg5r8hjzk6",
              "name": "Datacenters || RBX - RBX2",
              "old_status": "operational",
              "new_status": "operational"
            }
          ],
          "deliver_notifications": true,
          "custom_tweet": null,
          "tweet_id": null
        }
      ],
      "components": [
        {
          "id": "p5jg5r8hjzk6",
          "name": "RBX2",
          "status": "operational",
          "created_at": "2021-11-10T14:20:15.916Z",
          "updated_at": "2022-06-08T14:34:04.257Z",
          "position": 2,
          "description": null,
          "showcase": false,
          "start_date": "2021-11-10",
          "group_id": "zllgrccdn4nk",
          "page_id": "r3y8hrtg97vy",
          "group": false,
          "only_show_if_degraded": false
        }
      ],
      "scheduled_for": "2022-06-20T06:30:00.000Z",
      "scheduled_until": "2022-06-20T15:00:00.000Z"
    },
    {
      "id": "9n5f9rqt75b4",
      "name": "[BHS8][Infrastructure] - BHS0806A01C",
      "status": "scheduled",
      "created_at": "2022-06-14T19:15:28.351Z",
      "updated_at": "2022-06-14T19:16:49.535Z",
      "monitoring_at": null,
      "resolved_at": null,
      "impact": "maintenance",
      "shortlink": "https://stspg.io/4fb1tpphyb9z",
      "started_at": "2022-06-14T19:15:28.342Z",
      "page_id": "r3y8hrtg97vy",
      "incident_updates": [
        {
          "id": "rmd31tg434nd",
          "status": "scheduled",
          "body": "<b>Start time :</b> 20/06/2022 10:00 UTC\n<b>End time :</b> 20/06/2022 11:00 UTC\n<b>Service impact :</b> The 2 servers affected by this maintenance will be unreachable for 30 minutes.\n<b>Service improvement :</b> The maintenance objective is to replace electrical distribution equipment.",
          "incident_id": "9n5f9rqt75b4",
          "created_at": "2022-06-14T19:15:28.417Z",
          "updated_at": "2022-06-14T19:15:28.417Z",
          "display_at": "2022-06-14T19:15:28.417Z",
          "affected_components": [
            {
              "code": "m4pzrlrxvvgt",
              "name": "Infrastructure || BHS - BHS8",
              "old_status": "under_maintenance",
              "new_status": "under_maintenance"
            }
          ],
          "deliver_notifications": true,
          "custom_tweet": null,
          "tweet_id": null
        }
      ],
      "components": [
        {
          "id": "m4pzrlrxvvgt",
          "name": "BHS8",
          "status": "operational",
          "created_at": "2021-11-10T14:20:32.046Z",
          "updated_at": "2022-06-15T03:07:26.468Z",
          "position": 8,
          "description": null,
          "showcase": false,
          "start_date": "2021-11-10",
          "group_id": "p5hsr9gwdmns",
          "page_id": "r3y8hrtg97vy",
          "group": false,
          "only_show_if_degraded": false
        }
      ],
      "scheduled_for": "2022-06-20T10:00:00.000Z",
      "scheduled_until": "2022-06-20T11:00:00.000Z"
    },
    {
      "id": "nrk6dlksfcww",
      "name": "[BHS4][Infrastructure] - T04C24",
      "status": "scheduled",
      "created_at": "2022-06-14T18:56:38.763Z",
      "updated_at": "2022-06-14T18:56:38.829Z",
      "monitoring_at": null,
      "resolved_at": null,
      "impact": "maintenance",
      "shortlink": "https://stspg.io/315yk5gntf7k",
      "started_at": "2022-06-14T18:56:38.754Z",
      "page_id": "r3y8hrtg97vy",
      "incident_updates": [
        {
          "id": "wq49x4xq23kv",
          "status": "scheduled",
          "body": "<b>Start time :</b> 20/06/2022 11:00 UTC\n<b>End time :</b> 20/06/2022 19:30 UTC\n<b>Service impact :</b> None\n<b>Service improvement :</b> As part of our continuous improvement policy, we will be replacing faulty batteries on the altigo.",
          "incident_id": "nrk6dlksfcww",
          "created_at": "2022-06-14T18:56:38.826Z",
          "updated_at": "2022-06-14T18:56:38.826Z",
          "display_at": "2022-06-14T18:56:38.826Z",
          "affected_components": [
            {
              "code": "wjpq5n3hnjhx",
              "name": "Infrastructure || BHS - BHS4",
              "old_status": "operational",
              "new_status": "operational"
            }
          ],
          "deliver_notifications": true,
          "custom_tweet": null,
          "tweet_id": null
        }
      ],
      "components": [
        {
          "id": "wjpq5n3hnjhx",
          "name": "BHS4",
          "status": "operational",
          "created_at": "2021-11-10T14:20:28.786Z",
          "updated_at": "2022-06-09T19:16:07.915Z",
          "position": 4,
          "description": null,
          "showcase": false,
          "start_date": "2021-11-10",
          "group_id": "p5hsr9gwdmns",
          "page_id": "r3y8hrtg97vy",
          "group": false,
          "only_show_if_degraded": false
        }
      ],
      "scheduled_for": "2022-06-20T11:00:00.000Z",
      "scheduled_until": "2022-06-20T19:30:00.000Z"
    },
    {
      "id": "r6qsp9tjjh8k",
      "name": "[BHS4][Cooling System] - Rack T04D35",
      "status": "scheduled",
      "created_at": "2022-06-14T22:06:39.896Z",
      "updated_at": "2022-06-14T22:06:39.948Z",
      "monitoring_at": null,
      "resolved_at": null,
      "impact": "maintenance",
      "shortlink": "https://stspg.io/39ngksp6crh3",
      "started_at": "2022-06-14T22:06:39.889Z",
      "page_id": "r3y8hrtg97vy",
      "incident_updates": [
        {
          "id": "nr64tr7zks87",
          "status": "scheduled",
          "body": "<b>Start time :</b> 20/06/2022 11:00 UTC\n<b>End time :</b> 21/06/2022 03:00 UTC\n<b>Service impact :</b> None\n<b>Service improvement :</b> Water manifold replacement",
          "incident_id": "r6qsp9tjjh8k",
          "created_at": "2022-06-14T22:06:39.945Z",
          "updated_at": "2022-06-14T22:06:39.945Z",
          "display_at": "2022-06-14T22:06:39.945Z",
          "affected_components": [
            {
              "code": "wjpq5n3hnjhx",
              "name": "Infrastructure || BHS - BHS4",
              "old_status": "operational",
              "new_status": "operational"
            }
          ],
          "deliver_notifications": false,
          "custom_tweet": null,
          "tweet_id": null
        }
      ],
      "components": [
        {
          "id": "wjpq5n3hnjhx",
          "name": "BHS4",
          "status": "operational",
          "created_at": "2021-11-10T14:20:28.786Z",
          "updated_at": "2022-06-09T19:16:07.915Z",
          "position": 4,
          "description": null,
          "showcase": false,
          "start_date": "2021-11-10",
          "group_id": "p5hsr9gwdmns",
          "page_id": "r3y8hrtg97vy",
          "group": false,
          "only_show_if_degraded": false
        }
      ],
      "scheduled_for": "2022-06-20T20:00:00.000Z",
      "scheduled_until": "2022-06-21T12:00:00.000Z"
    },
    {
      "id": "dd5pzsrd91xg",
      "name": "[SBG3][Infrastructure] - Aircooling system",
      "status": "scheduled",
      "created_at": "2022-06-09T23:54:06.166Z",
      "updated_at": "2022-06-15T09:37:45.264Z",
      "monitoring_at": null,
      "resolved_at": null,
      "impact": "maintenance",
      "shortlink": "https://stspg.io/bthqcjbt7gnd",
      "started_at": "2022-06-09T23:54:06.159Z",
      "page_id": "r3y8hrtg97vy",
      "incident_updates": [
        {
          "id": "m03bpjktzw9x",
          "status": "scheduled",
          "body": "We will be undergoing scheduled maintenance during this time.",
          "incident_id": "dd5pzsrd91xg",
          "created_at": "2022-06-15T09:36:39.450Z",
          "updated_at": "2022-06-15T09:36:39.450Z",
          "display_at": "2022-06-15T09:36:39.450Z",
          "affected_components": [
            {
              "code": "n3pn0f28b99n",
              "name": "Infrastructure || SBG - SBG3",
              "old_status": "under_maintenance",
              "new_status": "under_maintenance"
            }
          ],
          "deliver_notifications": false,
          "custom_tweet": null,
          "tweet_id": null
        },
        {
          "id": "rx8c9t786ps2",
          "status": "scheduled",
          "body": "<b>Start time :</b> 20/06/2022 08:00 UTC\n<b>End time :</b> 20/06/2022 17:00 UTC\n<b>Service impact :</b> None\n<b>Service improvement :</b> This operation aims to improve our cooling systems by installing pockets at the outlet of the dry coolers in SBG3 MS8.",
          "incident_id": "dd5pzsrd91xg",
          "created_at": "2022-06-09T23:54:06.218Z",
          "updated_at": "2022-06-15T09:37:45.259Z",
          "display_at": "2022-06-09T23:54:06.218Z",
          "affected_components": [
            {
              "code": "n3pn0f28b99n",
              "name": "Infrastructure || SBG - SBG3",
              "old_status": "operational",
              "new_status": "operational"
            }
          ],
          "deliver_notifications": true,
          "custom_tweet": null,
          "tweet_id": null
        }
      ],
      "components": [
        {
          "id": "n3pn0f28b99n",
          "name": "SBG3",
          "status": "under_maintenance",
          "created_at": "2021-11-10T14:20:01.143Z",
          "updated_at": "2022-06-16T06:01:34.027Z",
          "position": 2,
          "description": null,
          "showcase": false,
          "start_date": "2021-11-10",
          "group_id": "vhfy3slw3nj2",
          "page_id": "r3y8hrtg97vy",
          "group": false,
          "only_show_if_degraded": false
        }
      ],
      "scheduled_for": "2022-06-22T08:00:00.000Z",
      "scheduled_until": "2022-06-22T17:00:00.000Z"
    },
    {
      "id": "t23y73k5kpf9",
      "name": "[LIM1][Network] - Network equipment version upgrade",
      "status": "scheduled",
      "created_at": "2022-06-10T08:46:19.032Z",
      "updated_at": "2022-06-10T08:46:19.088Z",
      "monitoring_at": null,
      "resolved_at": null,
      "impact": "maintenance",
      "shortlink": "https://stspg.io/w6kfnhjkzylr",
      "started_at": "2022-06-10T08:46:19.025Z",
      "page_id": "r3y8hrtg97vy",
      "incident_updates": [
        {
          "id": "xhmfvczp3pp2",
          "status": "scheduled",
          "body": "<b>Start time :</b> 22/06/2022 20:00 UTC\n<b>End time :</b> 22/06/2022 23:59 UTC\n<b>Service impact :</b> None\n<b>Service improvement :</b> In order to maintain continuous improvement of our internal network infrastructure and to have a homogeneous park, we will upgrade the version of 2 network equipment.",
          "incident_id": "t23y73k5kpf9",
          "created_at": "2022-06-10T08:46:19.085Z",
          "updated_at": "2022-06-10T08:46:19.085Z",
          "display_at": "2022-06-10T08:46:19.085Z",
          "affected_components": [
            {
              "code": "22t7pf7c6ky1",
              "name": "Infrastructure || LIM - LIM1",
              "old_status": "operational",
              "new_status": "operational"
            }
          ],
          "deliver_notifications": false,
          "custom_tweet": null,
          "tweet_id": null
        }
      ],
      "components": [
        {
          "id": "22t7pf7c6ky1",
          "name": "LIM1",
          "status": "operational",
          "created_at": "2021-11-10T14:19:53.034Z",
          "updated_at": "2022-06-10T01:50:36.080Z",
          "position": 1,
          "description": null,
          "showcase": false,
          "start_date": "2021-11-10",
          "group_id": "vmrgldv3x56g",
          "page_id": "r3y8hrtg97vy",
          "group": false,
          "only_show_if_degraded": false
        }
      ],
      "scheduled_for": "2022-06-22T20:00:00.000Z",
      "scheduled_until": "2022-06-22T23:59:00.000Z"
    },
    {
      "id": "55z5yb681lfm",
      "name": "[GRA3][Infrastructure]  Power Unit Commissioning in room NRJ",
      "status": "scheduled",
      "created_at": "2022-06-10T01:09:59.555Z",
      "updated_at": "2022-06-10T01:09:59.622Z",
      "monitoring_at": null,
      "resolved_at": null,
      "impact": "maintenance",
      "shortlink": "https://stspg.io/6s79kxhm1xzh",
      "started_at": "2022-06-10T01:09:59.547Z",
      "page_id": "r3y8hrtg97vy",
      "incident_updates": [
        {
          "id": "b5v6lc31mk17",
          "status": "scheduled",
          "body": "<b>Start time :</b> 27/06/2022 06:30 UTC\n<b>End time :</b> 05/07/2022 16:30 UTC\n<b>Service impact :</b> None\n<b>Service improvement  :</b> Commissioning an electrical unit",
          "incident_id": "55z5yb681lfm",
          "created_at": "2022-06-10T01:09:59.619Z",
          "updated_at": "2022-06-10T01:09:59.619Z",
          "display_at": "2022-06-10T01:09:59.619Z",
          "affected_components": [
            {
              "code": "mlw1x23q8nrt",
              "name": "Infrastructure || GRA - GRA3",
              "old_status": "operational",
              "new_status": "operational"
            }
          ],
          "deliver_notifications": true,
          "custom_tweet": null,
          "tweet_id": null
        }
      ],
      "components": [
        {
          "id": "mlw1x23q8nrt",
          "name": "GRA3",
          "status": "operational",
          "created_at": "2021-11-10T14:20:39.377Z",
          "updated_at": "2022-06-08T07:24:19.811Z",
          "position": 3,
          "description": null,
          "showcase": false,
          "start_date": "2021-11-10",
          "group_id": "cxhdwyc4lvgf",
          "page_id": "r3y8hrtg97vy",
          "group": false,
          "only_show_if_degraded": false
        }
      ],
      "scheduled_for": "2022-06-27T06:30:00.000Z",
      "scheduled_until": "2022-07-05T16:30:00.000Z"
    },
    {
      "id": "9wpq403s5svq",
      "name": "[ERI1][Infrastructure] - E103A17/E103A18",
      "status": "scheduled",
      "created_at": "2022-06-10T02:00:09.659Z",
      "updated_at": "2022-06-10T02:00:09.728Z",
      "monitoring_at": null,
      "resolved_at": null,
      "impact": "maintenance",
      "shortlink": "https://stspg.io/g2bhjt6mzrk2",
      "started_at": "2022-06-10T02:00:09.649Z",
      "page_id": "r3y8hrtg97vy",
      "incident_updates": [
        {
          "id": "m1bg83vzt38d",
          "status": "scheduled",
          "body": "<b>Start time :</b> 04/07/2022 07:00 UTC\n<b>End time :</b> 04/07/2022 17:00 UTC\n<b>Service impact :</b> Public network will be unreachable on racks E103A17 and  E103A18 for arround 30 minutes.\n<b>Service improvement :</b> The objective of this maintenance is to do electrical work to ensure continuity of services.",
          "incident_id": "9wpq403s5svq",
          "created_at": "2022-06-10T02:00:09.725Z",
          "updated_at": "2022-06-10T02:00:09.725Z",
          "display_at": "2022-06-10T02:00:09.725Z",
          "affected_components": [
            {
              "code": "l38v4l1b1vt8",
              "name": "Infrastructure || ERI - ERI1",
              "old_status": "under_maintenance",
              "new_status": "under_maintenance"
            }
          ],
          "deliver_notifications": true,
          "custom_tweet": null,
          "tweet_id": null
        }
      ],
      "components": [
        {
          "id": "l38v4l1b1vt8",
          "name": "ERI1",
          "status": "operational",
          "created_at": "2021-11-10T14:20:45.650Z",
          "updated_at": "2022-06-15T18:57:20.299Z",
          "position": 1,
          "description": null,
          "showcase": false,
          "start_date": "2021-11-10",
          "group_id": "sdpm85zsx4w3",
          "page_id": "r3y8hrtg97vy",
          "group": false,
          "only_show_if_degraded": false
        }
      ],
      "scheduled_for": "2022-07-04T07:00:00.000Z",
      "scheduled_until": "2022-07-04T15:00:00.000Z"
    },
    {
      "id": "x34tjhcm3jdt",
      "name": "[ERI1][Infrastructure] - E105A01 E105A02 E105A03 E105A04 E105A08 E105B09 E105B10 E105C11 E105C12",
      "status": "scheduled",
      "created_at": "2022-06-10T01:39:26.289Z",
      "updated_at": "2022-06-10T01:39:26.339Z",
      "monitoring_at": null,
      "resolved_at": null,
      "impact": "maintenance",
      "shortlink": "https://stspg.io/m2b6bgg7jz70",
      "started_at": "2022-06-10T01:39:26.283Z",
      "page_id": "r3y8hrtg97vy",
      "incident_updates": [
        {
          "id": "r6cr70d4zct0",
          "status": "scheduled",
          "body": "<b>Start time :</b> 04/07/2022 07:00 UTC\n<b>End time :</b> 04/07/2022 17:00 UTC\n<b>Service impact :</b> Public network will be unreachable on racks E105A01 E105A02 E105A03 E105A04 E105A08 E105B09 E105B10 E105C11 E105C12.\n<b>Service improvement :</b> The objective of this maintenance is to do electrical work to ensure continuity of services.",
          "incident_id": "x34tjhcm3jdt",
          "created_at": "2022-06-10T01:39:26.337Z",
          "updated_at": "2022-06-10T01:39:26.337Z",
          "display_at": "2022-06-10T01:39:26.337Z",
          "affected_components": [
            {
              "code": "l38v4l1b1vt8",
              "name": "Infrastructure || ERI - ERI1",
              "old_status": "under_maintenance",
              "new_status": "under_maintenance"
            }
          ],
          "deliver_notifications": true,
          "custom_tweet": null,
          "tweet_id": null
        }
      ],
      "components": [
        {
          "id": "l38v4l1b1vt8",
          "name": "ERI1",
          "status": "operational",
          "created_at": "2021-11-10T14:20:45.650Z",
          "updated_at": "2022-06-15T18:57:20.299Z",
          "position": 1,
          "description": null,
          "showcase": false,
          "start_date": "2021-11-10",
          "group_id": "sdpm85zsx4w3",
          "page_id": "r3y8hrtg97vy",
          "group": false,
          "only_show_if_degraded": false
        }
      ],
      "scheduled_for": "2022-07-04T07:00:00.000Z",
      "scheduled_until": "2022-07-04T17:00:00.000Z"
    },
    {
      "id": "b8tw30smntpy",
      "name": "[ERI1][Cooling System] - Rack E103C09",
      "status": "scheduled",
      "created_at": "2022-06-15T22:31:49.315Z",
      "updated_at": "2022-06-15T22:31:49.383Z",
      "monitoring_at": null,
      "resolved_at": null,
      "impact": "maintenance",
      "shortlink": "https://stspg.io/8xyxnbglq8pl",
      "started_at": "2022-06-15T22:31:49.307Z",
      "page_id": "r3y8hrtg97vy",
      "incident_updates": [
        {
          "id": "s45mbjsnmnb1",
          "status": "scheduled",
          "body": "<b>Start time :</b> 13/07/2022 06:00 UTC\n<b>End time :</b> 13/07/2022 10:00 UTC\n<b>Service impact :</b> The Rack will be power down during the operation.\n<b>Service improvement :</b> Cooling System replacement",
          "incident_id": "b8tw30smntpy",
          "created_at": "2022-06-15T22:31:49.381Z",
          "updated_at": "2022-06-15T22:31:49.381Z",
          "display_at": "2022-06-15T22:31:49.381Z",
          "affected_components": [
            {
              "code": "l38v4l1b1vt8",
              "name": "Infrastructure || ERI - ERI1",
              "old_status": "operational",
              "new_status": "operational"
            }
          ],
          "deliver_notifications": true,
          "custom_tweet": null,
          "tweet_id": null
        }
      ],
      "components": [
        {
          "id": "l38v4l1b1vt8",
          "name": "ERI1",
          "status": "operational",
          "created_at": "2021-11-10T14:20:45.650Z",
          "updated_at": "2022-06-15T18:57:20.299Z",
          "position": 1,
          "description": null,
          "showcase": false,
          "start_date": "2021-11-10",
          "group_id": "sdpm85zsx4w3",
          "page_id": "r3y8hrtg97vy",
          "group": false,
          "only_show_if_degraded": false
        }
      ],
      "scheduled_for": "2022-07-13T06:00:00.000Z",
      "scheduled_until": "2022-07-13T10:00:00.000Z"
    },
    {
      "id": "1z36mb072qdw",
      "name": "[ERI1][Cooling System] - Rack E103C15",
      "status": "scheduled",
      "created_at": "2022-06-15T22:31:46.293Z",
      "updated_at": "2022-06-15T22:31:46.395Z",
      "monitoring_at": null,
      "resolved_at": null,
      "impact": "maintenance",
      "shortlink": "https://stspg.io/qnbm2b74r4mp",
      "started_at": "2022-06-15T22:31:46.285Z",
      "page_id": "r3y8hrtg97vy",
      "incident_updates": [
        {
          "id": "f8tw3kkzwc1p",
          "status": "scheduled",
          "body": "<b>Start time :</b> 13/07/2022 10:00 UTC\n<b>End time :</b> 13/07/2022 14:00 UTC\n<b>Service impact :</b> The Rack will be power down during the operation.\n<b>Service improvement :</b>  Cooling System replacement",
          "incident_id": "1z36mb072qdw",
          "created_at": "2022-06-15T22:31:46.393Z",
          "updated_at": "2022-06-15T22:31:46.393Z",
          "display_at": "2022-06-15T22:31:46.393Z",
          "affected_components": [
            {
              "code": "l38v4l1b1vt8",
              "name": "Infrastructure || ERI - ERI1",
              "old_status": "operational",
              "new_status": "operational"
            }
          ],
          "deliver_notifications": true,
          "custom_tweet": null,
          "tweet_id": null
        }
      ],
      "components": [
        {
          "id": "l38v4l1b1vt8",
          "name": "ERI1",
          "status": "operational",
          "created_at": "2021-11-10T14:20:45.650Z",
          "updated_at": "2022-06-15T18:57:20.299Z",
          "position": 1,
          "description": null,
          "showcase": false,
          "start_date": "2021-11-10",
          "group_id": "sdpm85zsx4w3",
          "page_id": "r3y8hrtg97vy",
          "group": false,
          "only_show_if_degraded": false
        }
      ],
      "scheduled_for": "2022-07-13T10:00:00.000Z",
      "scheduled_until": "2022-07-13T14:00:00.000Z"
    },
    {
      "id": "dkrbfqgb3lgn",
      "name": "[RBX1][Infrastructure] UPS2 Battery",
      "status": "scheduled",
      "created_at": "2022-04-13T21:31:49.447Z",
      "updated_at": "2022-04-13T21:31:49.526Z",
      "monitoring_at": null,
      "resolved_at": null,
      "impact": "maintenance",
      "shortlink": "https://stspg.io/zpn4dz9pk4ns",
      "started_at": "2022-04-13T21:31:49.436Z",
      "page_id": "r3y8hrtg97vy",
      "incident_updates": [
        {
          "id": "ypfrnmt2c5p6",
          "status": "scheduled",
          "body": "<b>Start time :</b> 23/08/2022 06:00 UTC\n<b>End time :</b> 23/08/2022 15:00 UTC\n<b>Service impact :</b> None\n<b>Service improvement:</b> The objective of this maintenance is to carry out annual/curative maintenance of a UPS.",
          "incident_id": "dkrbfqgb3lgn",
          "created_at": "2022-04-13T21:31:49.522Z",
          "updated_at": "2022-04-13T21:31:49.522Z",
          "display_at": "2022-04-13T21:31:49.522Z",
          "affected_components": [
            {
              "code": "f4dnnwz43vr4",
              "name": "Datacenters || RBX - RBX1",
              "old_status": "operational",
              "new_status": "operational"
            }
          ],
          "deliver_notifications": true,
          "custom_tweet": null,
          "tweet_id": null
        }
      ],
      "components": [
        {
          "id": "f4dnnwz43vr4",
          "name": "RBX1",
          "status": "operational",
          "created_at": "2021-11-10T14:20:15.203Z",
          "updated_at": "2022-06-14T12:39:25.778Z",
          "position": 1,
          "description": null,
          "showcase": false,
          "start_date": "2021-11-10",
          "group_id": "zllgrccdn4nk",
          "page_id": "r3y8hrtg97vy",
          "group": false,
          "only_show_if_degraded": false
        }
      ],
      "scheduled_for": "2022-08-23T06:00:00.000Z",
      "scheduled_until": "2022-08-23T15:00:00.000Z"
    },
    {
      "id": "ryck6243fz00",
      "name": "[RBX1/RBX3/RBX8][Infrastructure] - Generator test",
      "status": "scheduled",
      "created_at": "2022-04-06T23:28:26.871Z",
      "updated_at": "2022-04-06T23:32:12.353Z",
      "monitoring_at": null,
      "resolved_at": null,
      "impact": "maintenance",
      "shortlink": "https://stspg.io/gskzmndw4ttt",
      "started_at": "2022-04-06T23:28:26.860Z",
      "page_id": "r3y8hrtg97vy",
      "incident_updates": [
        {
          "id": "d2ymj08v1fks",
          "status": "scheduled",
          "body": "<b>Start time :</b> 10/11/2022 07:30 UTC\n<b>End time :</b> 10/11/2022 16:00 UTC\n<b>Service impact :</b> None\n<b>Service improvement :</b> We will perform load tests on the generators.",
          "incident_id": "ryck6243fz00",
          "created_at": "2022-04-06T23:28:26.938Z",
          "updated_at": "2022-04-06T23:32:12.349Z",
          "display_at": "2022-04-06T23:28:26.938Z",
          "affected_components": [
            {
              "code": "f4dnnwz43vr4",
              "name": "Datacenters || RBX - RBX1",
              "old_status": "operational",
              "new_status": "operational"
            },
            {
              "code": "gmpjyy3kgdlv",
              "name": "Datacenters || RBX - RBX3",
              "old_status": "under_maintenance",
              "new_status": "under_maintenance"
            },
            {
              "code": "lpwtkmwp5rr2",
              "name": "Datacenters || RBX - RBX8",
              "old_status": "under_maintenance",
              "new_status": "under_maintenance"
            }
          ],
          "deliver_notifications": true,
          "custom_tweet": null,
          "tweet_id": null
        }
      ],
      "components": [
        {
          "id": "f4dnnwz43vr4",
          "name": "RBX1",
          "status": "operational",
          "created_at": "2021-11-10T14:20:15.203Z",
          "updated_at": "2022-06-14T12:39:25.778Z",
          "position": 1,
          "description": null,
          "showcase": false,
          "start_date": "2021-11-10",
          "group_id": "zllgrccdn4nk",
          "page_id": "r3y8hrtg97vy",
          "group": false,
          "only_show_if_degraded": false
        },
        {
          "id": "gmpjyy3kgdlv",
          "name": "RBX3",
          "status": "operational",
          "created_at": "2021-11-10T14:20:17.105Z",
          "updated_at": "2022-06-07T05:48:20.123Z",
          "position": 3,
          "description": null,
          "showcase": false,
          "start_date": "2021-11-10",
          "group_id": "zllgrccdn4nk",
          "page_id": "r3y8hrtg97vy",
          "group": false,
          "only_show_if_degraded": false
        },
        {
          "id": "lpwtkmwp5rr2",
          "name": "RBX8",
          "status": "operational",
          "created_at": "2021-11-10T14:20:20.804Z",
          "updated_at": "2022-06-14T16:50:27.219Z",
          "position": 8,
          "description": null,
          "showcase": false,
          "start_date": "2021-11-10",
          "group_id": "zllgrccdn4nk",
          "page_id": "r3y8hrtg97vy",
          "group": false,
          "only_show_if_degraded": false
        }
      ],
      "scheduled_for": "2022-11-10T07:30:00.000Z",
      "scheduled_until": "2022-11-10T16:00:00.000Z"
    },
    {
      "id": "wjk24r0zybsf",
      "name": "[US][Network] - Backbone maintenance",
      "status": "in_progress",
      "created_at": "2022-06-10T20:27:40.712Z",
      "updated_at": "2022-06-16T07:00:38.671Z",
      "monitoring_at": null,
      "resolved_at": null,
      "impact": "maintenance",
      "shortlink": "https://stspg.io/pv9166xzzb0l",
      "started_at": "2022-06-10T20:27:40.705Z",
      "page_id": "r3y8hrtg97vy",
      "incident_updates": [
        {
          "id": "70zq4gqp7rpt",
          "status": "in_progress",
          "body": "Scheduled maintenance is currently in progress. We will provide updates as necessary.",
          "incident_id": "wjk24r0zybsf",
          "created_at": "2022-06-16T07:00:38.663Z",
          "updated_at": "2022-06-16T07:00:38.663Z",
          "display_at": "2022-06-16T07:00:38.663Z",
          "affected_components": [
            {
              "code": "xxvy97qsff1g",
              "name": "Infrastructure || Backbone",
              "old_status": "operational",
              "new_status": "under_maintenance"
            }
          ],
          "deliver_notifications": true,
          "custom_tweet": null,
          "tweet_id": null
        },
        {
          "id": "wc7wk1bh66ms",
          "status": "scheduled",
          "body": "Maintenance will begin as scheduled in 60 minutes.",
          "incident_id": "wjk24r0zybsf",
          "created_at": "2022-06-16T06:00:23.975Z",
          "updated_at": "2022-06-16T06:00:23.975Z",
          "display_at": "2022-06-16T06:00:23.975Z",
          "affected_components": null,
          "deliver_notifications": true,
          "custom_tweet": null,
          "tweet_id": null
        },
        {
          "id": "v1g9s04dcm06",
          "status": "scheduled",
          "body": "<b>Start time :</b> 16/06/2022 07:00 UTC\n<b>End time :</b> 16/06/2022 09:00 UTC\n<b>Service impact :</b> None\n<b>Service improvement :</b> As part of our policy of continuous improvement of our network infrastructure, we are doing an internal maintenance on our US backbone.",
          "incident_id": "wjk24r0zybsf",
          "created_at": "2022-06-10T20:27:40.783Z",
          "updated_at": "2022-06-10T20:27:40.783Z",
          "display_at": "2022-06-10T20:27:40.783Z",
          "affected_components": [
            {
              "code": "xxvy97qsff1g",
              "name": "Infrastructure || Backbone",
              "old_status": "operational",
              "new_status": "operational"
            }
          ],
          "deliver_notifications": true,
          "custom_tweet": null,
          "tweet_id": null
        }
      ],
      "components": [
        {
          "id": "xxvy97qsff1g",
          "name": "Infrastructure || Backbone",
          "status": "under_maintenance",
          "created_at": "2022-05-20T08:38:13.277Z",
          "updated_at": "2022-06-16T07:00:38.596Z",
          "position": 1,
          "description": null,
          "showcase": false,
          "start_date": "2022-05-20",
          "group_id": null,
          "page_id": "r3y8hrtg97vy",
          "group": false,
          "only_show_if_degraded": false
        }
      ],
      "scheduled_for": "2022-06-16T07:00:00.000Z",
      "scheduled_until": "2022-06-16T09:00:00.000Z"
    },
    {
      "id": "j6znllcnl3ys",
      "name": "[SBG5][Infrastructure] - Cooling system S0500A and S0500B",
      "status": "in_progress",
      "created_at": "2022-06-15T20:26:54.523Z",
      "updated_at": "2022-06-16T06:01:44.678Z",
      "monitoring_at": null,
      "resolved_at": null,
      "impact": "maintenance",
      "shortlink": "https://stspg.io/k6746hjyhyz9",
      "started_at": "2022-06-15T20:26:54.518Z",
      "page_id": "r3y8hrtg97vy",
      "incident_updates": [
        {
          "id": "bnpr3z2jj37s",
          "status": "in_progress",
          "body": "Scheduled maintenance is currently in progress. We will provide updates as necessary.",
          "incident_id": "j6znllcnl3ys",
          "created_at": "2022-06-16T06:01:44.673Z",
          "updated_at": "2022-06-16T06:01:44.673Z",
          "display_at": "2022-06-16T06:01:44.673Z",
          "affected_components": null,
          "deliver_notifications": false,
          "custom_tweet": null,
          "tweet_id": null
        },
        {
          "id": "pb9cn3g3qvll",
          "status": "scheduled",
          "body": "<b>Start time :</b> 16/06/2022 06:00 UTC\n<b>End time :</b> 16/06/2022 15:00 UTC\n<b>Service impact :</b> None\n<b>Service improvement :</b> As part of our continuous improvement process of our infrastructure, we will be doing an operation on the cooling system of the rooms S0500A and S0500B.",
          "incident_id": "j6znllcnl3ys",
          "created_at": "2022-06-15T20:26:54.596Z",
          "updated_at": "2022-06-15T20:26:54.596Z",
          "display_at": "2022-06-15T20:26:54.596Z",
          "affected_components": null,
          "deliver_notifications": false,
          "custom_tweet": null,
          "tweet_id": null
        }
      ],
      "components": [],
      "scheduled_for": "2022-06-16T06:00:00.000Z",
      "scheduled_until": "2022-06-16T15:00:00.000Z"
    },
    {
      "id": "24dl732fm7nq",
      "name": "[SBG3][Infrastructure] - S324B01B",
      "status": "in_progress",
      "created_at": "2022-06-10T21:05:39.455Z",
      "updated_at": "2022-06-16T06:01:35.602Z",
      "monitoring_at": null,
      "resolved_at": null,
      "impact": "maintenance",
      "shortlink": "https://stspg.io/bt42y65lyjkq",
      "started_at": "2022-06-10T21:05:39.444Z",
      "page_id": "r3y8hrtg97vy",
      "incident_updates": [
        {
          "id": "76pddj8y0vw1",
          "status": "in_progress",
          "body": "Scheduled maintenance is currently in progress. We will provide updates as necessary.",
          "incident_id": "24dl732fm7nq",
          "created_at": "2022-06-16T06:01:35.596Z",
          "updated_at": "2022-06-16T06:01:35.596Z",
          "display_at": "2022-06-16T06:01:35.596Z",
          "affected_components": null,
          "deliver_notifications": true,
          "custom_tweet": null,
          "tweet_id": null
        },
        {
          "id": "m1zmwl4bg0c8",
          "status": "scheduled",
          "body": "Maintenance will begin as scheduled in 60 minutes.",
          "incident_id": "24dl732fm7nq",
          "created_at": "2022-06-16T05:00:24.851Z",
          "updated_at": "2022-06-16T05:00:24.851Z",
          "display_at": "2022-06-16T05:00:24.851Z",
          "affected_components": null,
          "deliver_notifications": true,
          "custom_tweet": null,
          "tweet_id": null
        },
        {
          "id": "wkxpfgdgz8qm",
          "status": "scheduled",
          "body": "<b>Start time :</b> 16/06/2022 06:00 UTC\n<b>End time :</b> 16/06/2022 15:00 UTC\n<b>Service impact :</b> None\n<b>Service improvement :</b> As part of our continuous improvement process of our infrastructure, we will be replacing UPS batteries.",
          "incident_id": "24dl732fm7nq",
          "created_at": "2022-06-10T21:05:39.528Z",
          "updated_at": "2022-06-10T21:05:39.528Z",
          "display_at": "2022-06-10T21:05:39.528Z",
          "affected_components": [
            {
              "code": "n3pn0f28b99n",
              "name": "Infrastructure || SBG - SBG3",
              "old_status": "operational",
              "new_status": "operational"
            }
          ],
          "deliver_notifications": true,
          "custom_tweet": null,
          "tweet_id": null
        }
      ],
      "components": [
        {
          "id": "n3pn0f28b99n",
          "name": "SBG3",
          "status": "under_maintenance",
          "created_at": "2021-11-10T14:20:01.143Z",
          "updated_at": "2022-06-16T06:01:34.027Z",
          "position": 2,
          "description": null,
          "showcase": false,
          "start_date": "2021-11-10",
          "group_id": "vhfy3slw3nj2",
          "page_id": "r3y8hrtg97vy",
          "group": false,
          "only_show_if_degraded": false
        }
      ],
      "scheduled_for": "2022-06-16T06:00:00.000Z",
      "scheduled_until": "2022-06-16T15:00:00.000Z"
    },
    {
      "id": "pt7bgs7vy6b2",
      "name": "[SBG3][Infrastructure] - S324B01A",
      "status": "in_progress",
      "created_at": "2022-06-10T21:01:37.117Z",
      "updated_at": "2022-06-16T06:01:35.320Z",
      "monitoring_at": null,
      "resolved_at": null,
      "impact": "maintenance",
      "shortlink": "https://stspg.io/21nky6w11q16",
      "started_at": "2022-06-10T21:01:37.108Z",
      "page_id": "r3y8hrtg97vy",
      "incident_updates": [
        {
          "id": "hn85v6mvwy11",
          "status": "in_progress",
          "body": "Scheduled maintenance is currently in progress. We will provide updates as necessary.",
          "incident_id": "pt7bgs7vy6b2",
          "created_at": "2022-06-16T06:01:35.312Z",
          "updated_at": "2022-06-16T06:01:35.312Z",
          "display_at": "2022-06-16T06:01:35.312Z",
          "affected_components": null,
          "deliver_notifications": true,
          "custom_tweet": null,
          "tweet_id": null
        },
        {
          "id": "rg0v37ck26zm",
          "status": "scheduled",
          "body": "Maintenance will begin as scheduled in 60 minutes.",
          "incident_id": "pt7bgs7vy6b2",
          "created_at": "2022-06-16T05:00:25.629Z",
          "updated_at": "2022-06-16T05:00:25.629Z",
          "display_at": "2022-06-16T05:00:25.629Z",
          "affected_components": null,
          "deliver_notifications": true,
          "custom_tweet": null,
          "tweet_id": null
        },
        {
          "id": "258n31q95chn",
          "status": "scheduled",
          "body": "<b>Start time :</b> 16/06/2022 06:00 UTC\n<b>End time :</b> 16/06/2022 15:00 UTC\n<b>Service impact :</b> None\n<b>Service improvement :</b> As part of our continuous improvement process of our infrastructure, we will be replacing UPS batteries.",
          "incident_id": "pt7bgs7vy6b2",
          "created_at": "2022-06-10T21:01:37.170Z",
          "updated_at": "2022-06-10T21:01:37.170Z",
          "display_at": "2022-06-10T21:01:37.170Z",
          "affected_components": [
            {
              "code": "n3pn0f28b99n",
              "name": "Infrastructure || SBG - SBG3",
              "old_status": "operational",
              "new_status": "operational"
            }
          ],
          "deliver_notifications": true,
          "custom_tweet": null,
          "tweet_id": null
        }
      ],
      "components": [
        {
          "id": "n3pn0f28b99n",
          "name": "SBG3",
          "status": "under_maintenance",
          "created_at": "2021-11-10T14:20:01.143Z",
          "updated_at": "2022-06-16T06:01:34.027Z",
          "position": 2,
          "description": null,
          "showcase": false,
          "start_date": "2021-11-10",
          "group_id": "vhfy3slw3nj2",
          "page_id": "r3y8hrtg97vy",
          "group": false,
          "only_show_if_degraded": false
        }
      ],
      "scheduled_for": "2022-06-16T06:00:00.000Z",
      "scheduled_until": "2022-06-16T15:00:00.000Z"
    },
    {
      "id": "vzykk4rfn0qd",
      "name": "[SBG3][Infrastructure] - Electrical work",
      "status": "in_progress",
      "created_at": "2022-06-09T22:46:49.080Z",
      "updated_at": "2022-06-16T06:01:34.757Z",
      "monitoring_at": null,
      "resolved_at": null,
      "impact": "maintenance",
      "shortlink": "https://stspg.io/c4h2t34gfcyq",
      "started_at": "2022-06-09T22:46:49.071Z",
      "page_id": "r3y8hrtg97vy",
      "incident_updates": [
        {
          "id": "6v5s78dkv2zy",
          "status": "in_progress",
          "body": "Scheduled maintenance is currently in progress. We will provide updates as necessary.",
          "incident_id": "vzykk4rfn0qd",
          "created_at": "2022-06-16T06:01:34.753Z",
          "updated_at": "2022-06-16T06:01:34.753Z",
          "display_at": "2022-06-16T06:01:34.753Z",
          "affected_components": null,
          "deliver_notifications": true,
          "custom_tweet": null,
          "tweet_id": null
        },
        {
          "id": "46jyrxgwk6lq",
          "status": "scheduled",
          "body": "Maintenance will begin as scheduled in 60 minutes.",
          "incident_id": "vzykk4rfn0qd",
          "created_at": "2022-06-16T05:00:23.031Z",
          "updated_at": "2022-06-16T05:00:23.031Z",
          "display_at": "2022-06-16T05:00:23.031Z",
          "affected_components": null,
          "deliver_notifications": true,
          "custom_tweet": null,
          "tweet_id": null
        },
        {
          "id": "2fcv25vvw07y",
          "status": "scheduled",
          "body": "<b>Start time :</b> 16/06/2022 06:00 UTC\n<b>End time :</b> 16/06/2022 15:00 UTC\n<b>Service impact :</b> None\n<b>Service improvement :</b> The purpose of this intervention is to replace the faulty UPS with one that is in good working order.",
          "incident_id": "vzykk4rfn0qd",
          "created_at": "2022-06-09T22:46:49.141Z",
          "updated_at": "2022-06-09T22:46:49.141Z",
          "display_at": "2022-06-09T22:46:49.141Z",
          "affected_components": [
            {
              "code": "n3pn0f28b99n",
              "name": "Infrastructure || SBG - SBG3",
              "old_status": "under_maintenance",
              "new_status": "under_maintenance"
            }
          ],
          "deliver_notifications": true,
          "custom_tweet": null,
          "tweet_id": null
        }
      ],
      "components": [
        {
          "id": "n3pn0f28b99n",
          "name": "SBG3",
          "status": "under_maintenance",
          "created_at": "2021-11-10T14:20:01.143Z",
          "updated_at": "2022-06-16T06:01:34.027Z",
          "position": 2,
          "description": null,
          "showcase": false,
          "start_date": "2021-11-10",
          "group_id": "vhfy3slw3nj2",
          "page_id": "r3y8hrtg97vy",
          "group": false,
          "only_show_if_degraded": false
        }
      ],
      "scheduled_for": "2022-06-16T06:00:00.000Z",
      "scheduled_until": "2022-06-16T15:00:00.000Z"
    },
    {
      "id": "51294lr2k871",
      "name": "[SBG][Infrastructure] - UPS batteries",
      "status": "in_progress",
      "created_at": "2022-06-09T15:11:58.078Z",
      "updated_at": "2022-06-16T06:01:34.144Z",
      "monitoring_at": null,
      "resolved_at": null,
      "impact": "maintenance",
      "shortlink": "https://stspg.io/x390s6qhsd7t",
      "started_at": "2022-06-09T15:11:58.069Z",
      "page_id": "r3y8hrtg97vy",
      "incident_updates": [
        {
          "id": "jygp7chyp4z7",
          "status": "in_progress",
          "body": "Scheduled maintenance is currently in progress. We will provide updates as necessary.",
          "incident_id": "51294lr2k871",
          "created_at": "2022-06-16T06:01:34.138Z",
          "updated_at": "2022-06-16T06:01:34.138Z",
          "display_at": "2022-06-16T06:01:34.138Z",
          "affected_components": [
            {
              "code": "2k7jxkf0w8f4",
              "name": "Infrastructure || SBG - SBG1",
              "old_status": "operational",
              "new_status": "under_maintenance"
            },
            {
              "code": "n3pn0f28b99n",
              "name": "Infrastructure || SBG - SBG3",
              "old_status": "operational",
              "new_status": "under_maintenance"
            },
            {
              "code": "n39cfc7qz4vh",
              "name": "Infrastructure || SBG - SBG4",
              "old_status": "operational",
              "new_status": "under_maintenance"
            }
          ],
          "deliver_notifications": true,
          "custom_tweet": null,
          "tweet_id": null
        },
        {
          "id": "gmvmlsswbk61",
          "status": "scheduled",
          "body": "Maintenance will begin as scheduled in 60 minutes.",
          "incident_id": "51294lr2k871",
          "created_at": "2022-06-16T05:00:29.110Z",
          "updated_at": "2022-06-16T05:00:29.110Z",
          "display_at": "2022-06-16T05:00:29.110Z",
          "affected_components": null,
          "deliver_notifications": true,
          "custom_tweet": null,
          "tweet_id": null
        },
        {
          "id": "jjqsd3mf6q1p",
          "status": "scheduled",
          "body": "<b>Start time :</b> 16/06/2022 06:00UTC\n<b>End time :</b> 16/06/2022 15:00UTC\n<b>Service impact :</b> We need to test UPS batteries (Uninterruptible Power Supply\n<b>Service improvement  :</b> What does it bring as improvement",
          "incident_id": "51294lr2k871",
          "created_at": "2022-06-09T15:11:58.129Z",
          "updated_at": "2022-06-09T15:11:58.129Z",
          "display_at": "2022-06-09T15:11:58.129Z",
          "affected_components": [
            {
              "code": "2k7jxkf0w8f4",
              "name": "Infrastructure || SBG - SBG1",
              "old_status": "under_maintenance",
              "new_status": "under_maintenance"
            },
            {
              "code": "n3pn0f28b99n",
              "name": "Infrastructure || SBG - SBG3",
              "old_status": "under_maintenance",
              "new_status": "under_maintenance"
            },
            {
              "code": "n39cfc7qz4vh",
              "name": "Infrastructure || SBG - SBG4",
              "old_status": "under_maintenance",
              "new_status": "under_maintenance"
            }
          ],
          "deliver_notifications": true,
          "custom_tweet": null,
          "tweet_id": null
        }
      ],
      "components": [
        {
          "id": "2k7jxkf0w8f4",
          "name": "SBG1",
          "status": "under_maintenance",
          "created_at": "2021-11-10T14:20:00.223Z",
          "updated_at": "2022-06-16T06:01:33.973Z",
          "position": 1,
          "description": null,
          "showcase": false,
          "start_date": "2021-11-10",
          "group_id": "vhfy3slw3nj2",
          "page_id": "r3y8hrtg97vy",
          "group": false,
          "only_show_if_degraded": false
        },
        {
          "id": "n3pn0f28b99n",
          "name": "SBG3",
          "status": "under_maintenance",
          "created_at": "2021-11-10T14:20:01.143Z",
          "updated_at": "2022-06-16T06:01:34.027Z",
          "position": 2,
          "description": null,
          "showcase": false,
          "start_date": "2021-11-10",
          "group_id": "vhfy3slw3nj2",
          "page_id": "r3y8hrtg97vy",
          "group": false,
          "only_show_if_degraded": false
        },
        {
          "id": "n39cfc7qz4vh",
          "name": "SBG4",
          "status": "under_maintenance",
          "created_at": "2021-11-10T14:20:01.976Z",
          "updated_at": "2022-06-16T06:01:34.060Z",
          "position": 3,
          "description": null,
          "showcase": false,
          "start_date": "2021-11-10",
          "group_id": "vhfy3slw3nj2",
          "page_id": "r3y8hrtg97vy",
          "group": false,
          "only_show_if_degraded": false
        }
      ],
      "scheduled_for": "2022-06-16T06:00:00.000Z",
      "scheduled_until": "2022-06-16T15:00:00.000Z"
    },
    {
      "id": "pk4cj06d6hbk",
      "name": "[GRA2][Cooling System] - G251A05",
      "status": "in_progress",
      "created_at": "2022-06-15T14:33:04.280Z",
      "updated_at": "2022-06-15T14:34:47.473Z",
      "monitoring_at": null,
      "resolved_at": null,
      "impact": "maintenance",
      "shortlink": "https://stspg.io/pbz49w02pgb2",
      "started_at": "2022-06-15T14:33:04.271Z",
      "page_id": "r3y8hrtg97vy",
      "incident_updates": [
        {
          "id": "15qyrd9gh2gr",
          "status": "in_progress",
          "body": "Scheduled maintenance is currently in progress. We will provide updates as necessary.",
          "incident_id": "pk4cj06d6hbk",
          "created_at": "2022-06-15T14:34:47.470Z",
          "updated_at": "2022-06-15T14:34:47.470Z",
          "display_at": "2022-06-15T14:34:47.470Z",
          "affected_components": [
            {
              "code": "f4vdn73g6790",
              "name": "Infrastructure || GRA - GRA2",
              "old_status": "operational",
              "new_status": "under_maintenance"
            }
          ],
          "deliver_notifications": true,
          "custom_tweet": null,
          "tweet_id": null
        },
        {
          "id": "py88k8bj3cwt",
          "status": "scheduled",
          "body": "<b>Start time :</b> 15/06/2022 12:00 UTC\n<b>End time :</b> 16/06/2022 14:00 UTC\n<b>Service impact :</b> None\n<b>Service improvement :</b> Water manifold replacement",
          "incident_id": "pk4cj06d6hbk",
          "created_at": "2022-06-15T14:33:04.335Z",
          "updated_at": "2022-06-15T14:33:04.335Z",
          "display_at": "2022-06-15T14:33:04.335Z",
          "affected_components": [
            {
              "code": "f4vdn73g6790",
              "name": "Infrastructure || GRA - GRA2",
              "old_status": "operational",
              "new_status": "operational"
            }
          ],
          "deliver_notifications": true,
          "custom_tweet": null,
          "tweet_id": null
        }
      ],
      "components": [
        {
          "id": "f4vdn73g6790",
          "name": "GRA2",
          "status": "under_maintenance",
          "created_at": "2021-11-10T14:20:38.598Z",
          "updated_at": "2022-06-15T14:34:47.424Z",
          "position": 2,
          "description": null,
          "showcase": false,
          "start_date": "2021-11-10",
          "group_id": "cxhdwyc4lvgf",
          "page_id": "r3y8hrtg97vy",
          "group": false,
          "only_show_if_degraded": false
        }
      ],
      "scheduled_for": "2022-06-15T14:34:00.000Z",
      "scheduled_until": "2022-06-16T14:00:00.000Z"
    },
    {
      "id": "d91cm6k6hrp7",
      "name": "[RBX7][Cooling System] - R718A10",
      "status": "in_progress",
      "created_at": "2022-06-14T09:57:54.021Z",
      "updated_at": "2022-06-14T11:57:38.308Z",
      "monitoring_at": null,
      "resolved_at": null,
      "impact": "maintenance",
      "shortlink": "https://stspg.io/rdmktgrj2q3n",
      "started_at": "2022-06-14T09:57:54.012Z",
      "page_id": "r3y8hrtg97vy",
      "incident_updates": [
        {
          "id": "30r511bmw87b",
          "status": "in_progress",
          "body": "Scheduled maintenance is currently in progress. We will provide updates as necessary.",
          "incident_id": "d91cm6k6hrp7",
          "created_at": "2022-06-14T11:57:38.303Z",
          "updated_at": "2022-06-14T11:57:38.303Z",
          "display_at": "2022-06-14T11:57:38.303Z",
          "affected_components": null,
          "deliver_notifications": true,
          "custom_tweet": null,
          "tweet_id": null
        },
        {
          "id": "p4p77gnj11yv",
          "status": "scheduled",
          "body": "Maintenance will begin as scheduled in 60 minutes.",
          "incident_id": "d91cm6k6hrp7",
          "created_at": "2022-06-14T10:57:22.865Z",
          "updated_at": "2022-06-14T10:57:22.865Z",
          "display_at": "2022-06-14T10:57:22.865Z",
          "affected_components": null,
          "deliver_notifications": true,
          "custom_tweet": null,
          "tweet_id": null
        },
        {
          "id": "65vx2x8jt5r9",
          "status": "scheduled",
          "body": "<b>Start time :</b> 14/06/2022 06:54 UTC\n<b>End time :</b> 21/06/2022 06:54 UTC\n<b>Service impact :</b> None\n<b>Service improvement :</b> Water manifold replacement",
          "incident_id": "d91cm6k6hrp7",
          "created_at": "2022-06-14T09:57:54.084Z",
          "updated_at": "2022-06-14T09:57:54.084Z",
          "display_at": "2022-06-14T09:57:54.084Z",
          "affected_components": [
            {
              "code": "02w2qqv00ll9",
              "name": "Infrastructure || RBX - RBX7",
              "old_status": "under_maintenance",
              "new_status": "under_maintenance"
            }
          ],
          "deliver_notifications": true,
          "custom_tweet": null,
          "tweet_id": null
        }
      ],
      "components": [
        {
          "id": "02w2qqv00ll9",
          "name": "RBX7",
          "status": "under_maintenance",
          "created_at": "2021-11-10T14:20:20.034Z",
          "updated_at": "2022-06-14T12:44:12.111Z",
          "position": 7,
          "description": null,
          "showcase": false,
          "start_date": "2021-11-10",
          "group_id": "zllgrccdn4nk",
          "page_id": "r3y8hrtg97vy",
          "group": false,
          "only_show_if_degraded": false
        }
      ],
      "scheduled_for": "2022-06-14T11:57:00.000Z",
      "scheduled_until": "2022-06-21T06:55:00.000Z"
    },
    {
      "id": "ly3l4r5cqvbx",
      "name": "[GRA1][Infrastructure] - Electrical works",
      "status": "in_progress",
      "created_at": "2022-06-09T23:00:47.476Z",
      "updated_at": "2022-06-13T06:10:35.285Z",
      "monitoring_at": null,
      "resolved_at": null,
      "impact": "maintenance",
      "shortlink": "https://stspg.io/192kj146gts1",
      "started_at": "2022-06-09T23:00:47.468Z",
      "page_id": "r3y8hrtg97vy",
      "incident_updates": [
        {
          "id": "cgcgc6hh7pcd",
          "status": "in_progress",
          "body": "Scheduled maintenance is currently in progress. We will provide updates as necessary.",
          "incident_id": "ly3l4r5cqvbx",
          "created_at": "2022-06-13T06:10:35.281Z",
          "updated_at": "2022-06-13T06:10:35.281Z",
          "display_at": "2022-06-13T06:10:35.281Z",
          "affected_components": [
            {
              "code": "66ctp89pwlcd",
              "name": "Infrastructure || GRA - GRA1",
              "old_status": "operational",
              "new_status": "under_maintenance"
            }
          ],
          "deliver_notifications": true,
          "custom_tweet": null,
          "tweet_id": null
        },
        {
          "id": "hflzgtcxtc5m",
          "status": "scheduled",
          "body": "Maintenance will begin as scheduled in 60 minutes.",
          "incident_id": "ly3l4r5cqvbx",
          "created_at": "2022-06-13T05:10:22.729Z",
          "updated_at": "2022-06-13T05:10:22.729Z",
          "display_at": "2022-06-13T05:10:22.729Z",
          "affected_components": null,
          "deliver_notifications": true,
          "custom_tweet": null,
          "tweet_id": null
        },
        {
          "id": "r2b19ph0kwgh",
          "status": "scheduled",
          "body": "<b>Start time :</b> 13/06/2022 06:10 UTC\n<b>End time :</b> 16/06/2022 14:11 UTC\n<b>Service impact :</b> None\n<b>Service improvement :</b> Adding of a circuit breaker on the normaclip of the cabinets.",
          "incident_id": "ly3l4r5cqvbx",
          "created_at": "2022-06-09T23:00:47.526Z",
          "updated_at": "2022-06-09T23:00:47.526Z",
          "display_at": "2022-06-09T23:00:47.526Z",
          "affected_components": [
            {
              "code": "66ctp89pwlcd",
              "name": "Infrastructure || GRA - GRA1",
              "old_status": "operational",
              "new_status": "operational"
            }
          ],
          "deliver_notifications": true,
          "custom_tweet": null,
          "tweet_id": null
        }
      ],
      "components": [
        {
          "id": "66ctp89pwlcd",
          "name": "GRA1",
          "status": "operational",
          "created_at": "2021-11-10T14:20:37.816Z",
          "updated_at": "2022-06-16T02:03:40.679Z",
          "position": 1,
          "description": null,
          "showcase": false,
          "start_date": "2021-11-10",
          "group_id": "cxhdwyc4lvgf",
          "page_id": "r3y8hrtg97vy",
          "group": false,
          "only_show_if_degraded": false
        }
      ],
      "scheduled_for": "2022-06-13T06:10:00.000Z",
      "scheduled_until": "2022-06-13T14:11:00.000Z"
    }
  ],
  "status": {
    "indicator": "maintenance",
    "description": "Service Under Maintenance"
  }
}
